{
  "ComponentIndexes": {},
  "ControlUniqueGuids": {},
  "ControlUniqueIds": {
    "admin_screen": 157,
    "admin_screen_pres": 45,
    "admin_screen_searchUsers": 166,
    "admin_screen_sendIntakes": 4,
    "admin_screen_users": 15,
    "admin_screen_viewUser": 55,
    "App": 1,
    "Button1_1": 154,
    "Button1_2": 156,
    "Button1_3": 155,
    "Button2": 82,
    "Button2_1": 174,
    "Button2_10": 162,
    "Button2_11": 88,
    "Button2_12": 89,
    "Button2_13": 19,
    "Button2_14": 20,
    "Button2_15": 59,
    "Button2_16": 60,
    "Button2_17": 170,
    "Button2_18": 171,
    "Button2_19": 9,
    "Button2_2": 63,
    "Button2_21": 50,
    "Button2_3": 79,
    "Button2_5": 8,
    "Button2_8": 49,
    "Button2_9": 161,
    "Button3": 78,
    "Button3_1": 42,
    "Button4": 43,
    "Button4_1": 44,
    "Container1": 80,
    "Container2": 10,
    "Container2_2": 163,
    "Container2_3": 21,
    "Container2_4": 61,
    "Container2_5": 172,
    "Container2_6": 51,
    "courseGoal_DataCard1": 142,
    "currentFunction_DataCard1": 130,
    "DataCardKey1": 24,
    "DataCardKey10": 128,
    "DataCardKey11": 131,
    "DataCardKey12": 134,
    "DataCardKey13": 137,
    "DataCardKey14": 27,
    "DataCardKey15": 30,
    "DataCardKey16": 140,
    "DataCardKey17": 143,
    "DataCardKey18": 146,
    "DataCardKey2": 100,
    "DataCardKey3": 104,
    "DataCardKey36": 151,
    "DataCardKey4": 109,
    "DataCardKey5": 113,
    "DataCardKey6": 116,
    "DataCardKey7": 119,
    "DataCardKey8": 122,
    "DataCardKey9": 125,
    "DataCardValue1": 25,
    "DataCardValue10": 129,
    "DataCardValue11": 132,
    "DataCardValue12": 135,
    "DataCardValue13": 138,
    "DataCardValue14": 28,
    "DataCardValue15": 31,
    "DataCardValue16": 141,
    "DataCardValue17": 144,
    "DataCardValue18": 147,
    "DataCardValue2": 101,
    "DataCardValue3": 105,
    "DataCardValue35": 152,
    "DataCardValue4": 110,
    "DataCardValue5": 114,
    "DataCardValue6": 117,
    "DataCardValue7": 120,
    "DataCardValue8": 123,
    "DataCardValue9": 126,
    "dateOfBirth_DataCard1": 118,
    "education_DataCard1": 127,
    "email_address_input": 14,
    "email_DataCard1": 121,
    "email_DataCard2": 23,
    "ErrorMessage1": 106,
    "ErrorMessage2": 111,
    "ErrorMessage21": 153,
    "FormInspection": 148,
    "FormViewer1": 98,
    "FormViewer2": 22,
    "fullname_DataCard1": 112,
    "fullName_DataCard1": 26,
    "functionExplained_DataCard1": 133,
    "Gallery1": 34,
    "Gallery2": 71,
    "Gallery3_1": 173,
    "Gallery6": 178,
    "GalleryInspection": 90,
    "galleryTemplate1": 91,
    "galleryTemplate2": 35,
    "galleryTemplate3": 72,
    "galleryTemplate4_1": 175,
    "galleryTemplate7": 180,
    "gender_DataCard1": 115,
    "Host": 3,
    "Icon1": 81,
    "Icon5": 177,
    "Icon5_1": 33,
    "ID_DataCard1": 99,
    "Image1": 93,
    "Image2": 37,
    "Image4": 54,
    "Image5": 181,
    "intake_screen": 84,
    "intakeNavButton_1": 7,
    "intakeNavButton_3": 160,
    "intakeNavButton_4": 87,
    "intakeNavButton_5": 18,
    "intakeNavButton_6": 58,
    "intakeNavButton_7": 169,
    "intakeNavButton_8": 48,
    "Label1_1": 6,
    "Label1_3": 159,
    "Label1_4": 86,
    "Label1_5": 17,
    "Label1_6": 57,
    "Label1_7": 168,
    "Label1_8": 47,
    "Label2": 65,
    "Label2_1": 68,
    "Label2_2": 64,
    "Label2_3": 67,
    "Label2_4": 70,
    "Label2_5": 69,
    "Label2_6": 77,
    "Label2_7": 76,
    "Label3": 52,
    "Label3_1": 12,
    "Label4": 53,
    "Label4_1": 164,
    "Label4_2": 165,
    "Label5": 11,
    "Label6": 62,
    "Label6_1": 66,
    "navBarAdmin_1": 5,
    "navBarAdmin_3": 158,
    "navBarAdmin_4": 85,
    "navBarAdmin_5": 16,
    "navBarAdmin_6": 56,
    "navBarAdmin_7": 167,
    "navBarAdmin_8": 46,
    "NextArrow1": 94,
    "NextArrow2": 38,
    "NextArrow4": 182,
    "phoneNumber_DataCard1": 124,
    "phoneNumber_DataCard2": 29,
    "programmingExperience_DataCard1": 102,
    "programmingLanguage_DataCard1": 139,
    "Rectangle1": 92,
    "Rectangle2": 36,
    "Rectangle3": 73,
    "Rectangle4": 179,
    "Separator1": 97,
    "Separator2": 41,
    "Separator3": 75,
    "Separator4": 185,
    "StarVisible1": 103,
    "StarVisible2": 108,
    "StarVisible21": 150,
    "status_DataCard2": 107,
    "status_DataCard7": 149,
    "studentID_DataCard1": 145,
    "submit_sendEmail": 13,
    "Subtitle1": 96,
    "Subtitle2": 40,
    "Subtitle5": 184,
    "TextInput1": 83,
    "Title1": 95,
    "Title2": 39,
    "Title3": 74,
    "Title5": 183,
    "txtSearch": 176,
    "txtSearch_1": 32,
    "yearsExperience_DataCard1": 136
  },
  "FunctionParamsInvariantScripts": {},
  "FunctionParamsInvariantScriptsOnInstances": {},
  "HeaderLastSavedDateTimeUTC": "02/29/2024 13:38:28",
  "IsLegacyComponentAllowGlobalScopeCase": false,
  "LocalConnectionIDReferences": {
    "00106cf0-ef67-4cd9-818e-824fd17124f7": "\"/providers/microsoft.powerapps/apis/shared_sharepointonline/connections/18ed636a42a64d74a4351771b0a35296\"",
    "2465da9a-867f-4f65-82ac-cb2d268f4384": "\"/providers/microsoft.powerapps/apis/shared_logicflows/connections/e5c3ba22281b44ca9d91ef3ccd6adf24-e4f895229d9d1dd7\"",
    "5950dfa2-140f-4c8e-a6b5-d0ac3f9b439b": "\"/providers/microsoft.powerapps/apis/shared_logicflows/connections/e109796b8d2a4a6cbc4cd3a4dee5a8a8-e4f895229d9d1dd7\"",
    "c1990989-d1b3-409a-8532-7a50671b4cd9": "\"/providers/microsoft.powerapps/apis/shared_office365/connections/5830176a1b044b108e62069c66ef21ed\""
  },
  "LocalDatabaseReferencesAsEmpty": false,
  "LocalResourceFileNames": {
    "2021-logo-tech_power-apps-nobg": "03f79e29-24ee-487d-9fb5-824d90ff6343.png",
    "work-at-layer": "0001.jpg"
  },
  "LocalResourceRootPaths": {
    "2021-logo-tech_power-apps-nobg": "https://docserverpwaprodneu.blob.core.windows.net/ae1e1b81-be2c-4e52-9fae-02d06de1025e-1/resource/Assets0Images003f79e29-24ee-487d-9fb5-824d90ff6343.png?skoid=58690ece-ec83-4ce2-9ce8-883d4d6a54ee&sktid=975f013f-7f24-47e8-a7d3-abc4752bf346&skt=2024-02-29T11%3A54%3A27Z&ske=2024-03-01T12%3A09%3A27Z&sks=b&skv=2022-11-02&sv=2022-11-02&spr=https&se=2024-03-01T12%3A09%3A27Z&sr=b&sp=r&sig=bpQteClGSkhVMw9U7C17EwW1HJIWxUKGpu0%2FjTOLIro%3D",
    "work-at-layer": "https://docserverpwaprodneu.blob.core.windows.net/ae1e1b81-be2c-4e52-9fae-02d06de1025e-1/resource/Assets0Images00001.jpg?skoid=58690ece-ec83-4ce2-9ce8-883d4d6a54ee&sktid=975f013f-7f24-47e8-a7d3-abc4752bf346&skt=2024-02-29T11%3A54%3A27Z&ske=2024-03-01T12%3A09%3A27Z&sks=b&skv=2022-11-02&sv=2022-11-02&spr=https&se=2024-03-01T12%3A09%3A27Z&sr=b&sp=r&sig=ewUsW2ZgYCxWT6w58kKfSlKZsa19P6w0z8nnR93trTI%3D"
  },
  "OrderComponentMetadata": {},
  "OrderComponentTemplate": {},
  "OrderDataSource": {
    "ComboBoxSample": 14,
    "CreateUserForIntake": 0,
    "CustomGallerySample": 15,
    "DropDownSample": 16,
    "intakeResults": 17,
    "Nieuwe tabellen": 19,
    "Nieuwe tabellen\\cr884_nieuwetabel_cr884_programmingexperience": 3,
    "Nieuwe tabellen\\cr884_nieuwetabel_cr884_status": 4,
    "Nieuwe tabellen\\cr884_nieuwetabel_statecode": 5,
    "Nieuwe tabellen\\cr884_nieuwetabel_statuscode": 6,
    "Nieuwe tabellen\\default.cds_cr884_nieuwetabel_views": 11,
    "Nieuwe tabellen_1": 20,
    "Nieuwe tabellen_1\\cr884_nieuwetabel2_statecode": 7,
    "Nieuwe tabellen_1\\cr884_nieuwetabel2_statuscode": 8,
    "Nieuwe tabellen_1\\default.cds_cr884_nieuwetabel2_views": 12,
    "Office365Outlook": 1,
    "PowerAppV2->Itemmaken": 2,
    "scores": 21,
    "scores\\cr884_scores_statecode": 9,
    "scores\\cr884_scores_statuscode": 10,
    "scores\\default.cds_cr884_scores_views": 13,
    "students": 18,
    "userData": 22
  },
  "OrderGroupControls": {},
  "OrderPcfTemplate": {},
  "OrderTemplate": {},
  "OrderXMLTemplate": {
    "button": 2,
    "combobox": 9,
    "form": 10,
    "formViewer": 5,
    "gallery": 7,
    "groupContainer": 3,
    "icon": 6,
    "image": 8,
    "label": 1,
    "rectangle": 0,
    "text": 4
  },
  "OverridablePropertiesEntry": {
    "admin_screen": {},
    "admin_screen_pres": {},
    "admin_screen_searchUsers": {},
    "admin_screen_sendIntakes": {},
    "admin_screen_users": {},
    "admin_screen_viewUser": {},
    "App": {},
    "Button1_1": {},
    "Button1_2": {},
    "Button1_3": {},
    "Button2": {},
    "Button2_1": {},
    "Button2_10": {},
    "Button2_11": {},
    "Button2_12": {},
    "Button2_13": {},
    "Button2_14": {},
    "Button2_15": {},
    "Button2_16": {},
    "Button2_17": {},
    "Button2_18": {},
    "Button2_19": {},
    "Button2_2": {},
    "Button2_21": {},
    "Button2_3": {},
    "Button2_5": {},
    "Button2_8": {},
    "Button2_9": {},
    "Button3": {},
    "Button3_1": {},
    "Button4": {},
    "Button4_1": {},
    "Container1": {},
    "Container2": {},
    "Container2_2": {},
    "Container2_3": {},
    "Container2_4": {},
    "Container2_5": {},
    "Container2_6": {},
    "courseGoal_DataCard1": {},
    "currentFunction_DataCard1": {},
    "DataCardKey1": {},
    "DataCardKey10": {},
    "DataCardKey11": {},
    "DataCardKey12": {},
    "DataCardKey13": {},
    "DataCardKey14": {},
    "DataCardKey15": {},
    "DataCardKey16": {},
    "DataCardKey17": {},
    "DataCardKey18": {},
    "DataCardKey2": {},
    "DataCardKey3": {},
    "DataCardKey36": {},
    "DataCardKey4": {},
    "DataCardKey5": {},
    "DataCardKey6": {},
    "DataCardKey7": {},
    "DataCardKey8": {},
    "DataCardKey9": {},
    "DataCardValue1": {},
    "DataCardValue10": {},
    "DataCardValue11": {},
    "DataCardValue12": {},
    "DataCardValue13": {},
    "DataCardValue14": {},
    "DataCardValue15": {},
    "DataCardValue16": {},
    "DataCardValue17": {},
    "DataCardValue18": {},
    "DataCardValue2": {},
    "DataCardValue3": {},
    "DataCardValue35": {},
    "DataCardValue4": {},
    "DataCardValue5": {},
    "DataCardValue6": {},
    "DataCardValue7": {},
    "DataCardValue8": {},
    "DataCardValue9": {},
    "dateOfBirth_DataCard1": {},
    "education_DataCard1": {},
    "email_address_input": {},
    "email_DataCard1": {},
    "email_DataCard2": {},
    "ErrorMessage1": {},
    "ErrorMessage2": {},
    "ErrorMessage21": {},
    "FormInspection": {},
    "FormViewer1": {},
    "FormViewer2": {},
    "fullname_DataCard1": {},
    "fullName_DataCard1": {},
    "functionExplained_DataCard1": {},
    "Gallery1": {},
    "Gallery2": {},
    "Gallery3_1": {},
    "Gallery6": {},
    "GalleryInspection": {},
    "galleryTemplate1": {},
    "galleryTemplate2": {},
    "galleryTemplate3": {},
    "galleryTemplate4_1": {},
    "galleryTemplate7": {},
    "gender_DataCard1": {},
    "Host": {},
    "Icon1": {},
    "Icon5": {},
    "Icon5_1": {},
    "ID_DataCard1": {},
    "Image1": {},
    "Image2": {},
    "Image4": {},
    "Image5": {},
    "intake_screen": {},
    "intakeNavButton_1": {},
    "intakeNavButton_3": {},
    "intakeNavButton_4": {},
    "intakeNavButton_5": {},
    "intakeNavButton_6": {},
    "intakeNavButton_7": {},
    "intakeNavButton_8": {},
    "Label1_1": {},
    "Label1_3": {},
    "Label1_4": {},
    "Label1_5": {},
    "Label1_6": {},
    "Label1_7": {},
    "Label1_8": {},
    "Label2": {},
    "Label2_1": {},
    "Label2_2": {},
    "Label2_3": {},
    "Label2_4": {},
    "Label2_5": {},
    "Label2_6": {},
    "Label2_7": {},
    "Label3": {},
    "Label3_1": {},
    "Label4": {},
    "Label4_1": {},
    "Label4_2": {},
    "Label5": {},
    "Label6": {},
    "Label6_1": {},
    "navBarAdmin_1": {},
    "navBarAdmin_3": {},
    "navBarAdmin_4": {},
    "navBarAdmin_5": {},
    "navBarAdmin_6": {},
    "navBarAdmin_7": {},
    "navBarAdmin_8": {},
    "NextArrow1": {},
    "NextArrow2": {},
    "NextArrow4": {},
    "phoneNumber_DataCard1": {},
    "phoneNumber_DataCard2": {},
    "programmingExperience_DataCard1": {},
    "programmingLanguage_DataCard1": {},
    "Rectangle1": {},
    "Rectangle2": {},
    "Rectangle3": {},
    "Rectangle4": {},
    "Separator1": {},
    "Separator2": {},
    "Separator3": {},
    "Separator4": {},
    "StarVisible1": {},
    "StarVisible2": {},
    "StarVisible21": {},
    "status_DataCard2": {},
    "status_DataCard7": {},
    "studentID_DataCard1": {},
    "submit_sendEmail": {},
    "Subtitle1": {},
    "Subtitle2": {},
    "Subtitle5": {},
    "TextInput1": {},
    "Title1": {},
    "Title2": {},
    "Title3": {},
    "Title5": {},
    "txtSearch": {},
    "txtSearch_1": {},
    "yearsExperience_DataCard1": {}
  },
  "PCFDynamicSchemaForIRRetrievalEntry": {},
  "PCFTemplateEntry": {},
  "PublishOrderIndices": {
    "admin_screen": 1,
    "admin_screen_pres": 41,
    "admin_screen_searchUsers": 10,
    "admin_screen_sendIntakes": 30,
    "admin_screen_users": 48,
    "admin_screen_viewUser": 75,
    "App": 0,
    "Button1_1": 77,
    "Button1_2": 79,
    "Button1_3": 78,
    "Button2": 135,
    "Button2_1": 144,
    "Button2_10": 4,
    "Button2_11": 11,
    "Button2_12": 12,
    "Button2_13": 83,
    "Button2_14": 84,
    "Button2_15": 112,
    "Button2_16": 113,
    "Button2_17": 140,
    "Button2_18": 141,
    "Button2_19": 160,
    "Button2_2": 116,
    "Button2_21": 170,
    "Button2_3": 132,
    "Button2_5": 159,
    "Button2_8": 169,
    "Button2_9": 3,
    "Button3": 131,
    "Button3_1": 106,
    "Button4": 107,
    "Button4_1": 108,
    "Container1": 133,
    "Container2": 161,
    "Container2_2": 5,
    "Container2_3": 85,
    "Container2_4": 114,
    "Container2_5": 142,
    "Container2_6": 171,
    "courseGoal_DataCard1": 65,
    "currentFunction_DataCard1": 53,
    "DataCardKey1": 88,
    "DataCardKey10": 51,
    "DataCardKey11": 54,
    "DataCardKey12": 57,
    "DataCardKey13": 60,
    "DataCardKey14": 91,
    "DataCardKey15": 94,
    "DataCardKey16": 63,
    "DataCardKey17": 66,
    "DataCardKey18": 69,
    "DataCardKey2": 23,
    "DataCardKey3": 27,
    "DataCardKey36": 74,
    "DataCardKey4": 32,
    "DataCardKey5": 36,
    "DataCardKey6": 39,
    "DataCardKey7": 42,
    "DataCardKey8": 45,
    "DataCardKey9": 48,
    "DataCardValue1": 89,
    "DataCardValue10": 52,
    "DataCardValue11": 55,
    "DataCardValue12": 58,
    "DataCardValue13": 61,
    "DataCardValue14": 92,
    "DataCardValue15": 95,
    "DataCardValue16": 64,
    "DataCardValue17": 67,
    "DataCardValue18": 70,
    "DataCardValue2": 24,
    "DataCardValue3": 28,
    "DataCardValue35": 75,
    "DataCardValue4": 33,
    "DataCardValue5": 37,
    "DataCardValue6": 40,
    "DataCardValue7": 43,
    "DataCardValue8": 46,
    "DataCardValue9": 49,
    "dateOfBirth_DataCard1": 41,
    "education_DataCard1": 50,
    "email_address_input": 165,
    "email_DataCard1": 44,
    "email_DataCard2": 87,
    "ErrorMessage1": 29,
    "ErrorMessage2": 34,
    "ErrorMessage21": 76,
    "FormInspection": 71,
    "FormViewer1": 21,
    "FormViewer2": 86,
    "fullname_DataCard1": 35,
    "fullName_DataCard1": 90,
    "functionExplained_DataCard1": 56,
    "Gallery1": 98,
    "Gallery2": 124,
    "Gallery3_1": 143,
    "Gallery6": 148,
    "GalleryInspection": 13,
    "galleryTemplate1": 14,
    "galleryTemplate2": 99,
    "galleryTemplate3": 125,
    "galleryTemplate4_1": 145,
    "galleryTemplate7": 150,
    "gender_DataCard1": 38,
    "Host": 0,
    "Icon1": 134,
    "Icon5": 147,
    "Icon5_1": 97,
    "ID_DataCard1": 22,
    "Image1": 16,
    "Image2": 101,
    "Image4": 174,
    "Image5": 151,
    "intake_screen": 95,
    "intakeNavButton_1": 158,
    "intakeNavButton_3": 2,
    "intakeNavButton_4": 10,
    "intakeNavButton_5": 82,
    "intakeNavButton_6": 111,
    "intakeNavButton_7": 139,
    "intakeNavButton_8": 168,
    "Label1_1": 157,
    "Label1_3": 1,
    "Label1_4": 9,
    "Label1_5": 81,
    "Label1_6": 110,
    "Label1_7": 138,
    "Label1_8": 167,
    "Label2": 118,
    "Label2_1": 121,
    "Label2_2": 117,
    "Label2_3": 120,
    "Label2_4": 123,
    "Label2_5": 122,
    "Label2_6": 130,
    "Label2_7": 129,
    "Label3": 172,
    "Label3_1": 163,
    "Label4": 173,
    "Label4_1": 6,
    "Label4_2": 7,
    "Label5": 162,
    "Label6": 115,
    "Label6_1": 119,
    "navBarAdmin_1": 156,
    "navBarAdmin_3": 0,
    "navBarAdmin_4": 8,
    "navBarAdmin_5": 80,
    "navBarAdmin_6": 109,
    "navBarAdmin_7": 137,
    "navBarAdmin_8": 166,
    "NextArrow1": 17,
    "NextArrow2": 102,
    "NextArrow4": 152,
    "phoneNumber_DataCard1": 47,
    "phoneNumber_DataCard2": 93,
    "programmingExperience_DataCard1": 25,
    "programmingLanguage_DataCard1": 62,
    "Rectangle1": 15,
    "Rectangle2": 100,
    "Rectangle3": 126,
    "Rectangle4": 149,
    "Separator1": 20,
    "Separator2": 105,
    "Separator3": 128,
    "Separator4": 155,
    "StarVisible1": 26,
    "StarVisible2": 31,
    "StarVisible21": 73,
    "status_DataCard2": 30,
    "status_DataCard7": 72,
    "studentID_DataCard1": 68,
    "submit_sendEmail": 164,
    "Subtitle1": 19,
    "Subtitle2": 104,
    "Subtitle5": 154,
    "TextInput1": 136,
    "Title1": 18,
    "Title2": 103,
    "Title3": 127,
    "Title5": 153,
    "txtSearch": 146,
    "txtSearch_1": 96,
    "yearsExperience_DataCard1": 59
  },
  "ResourcesJsonIndices": {
    "Image-2021-logo-tech_power-apps-nobg": 2,
    "Image-SampleImage": 0,
    "Image-work-at-layer": 1
  },
  "RuleScreenIdWithoutScreen": {},
  "TemplateVersions": {},
  "VolatileProperties": {
    "AnalysisLoadTime": 0.8458847,
    "ControlCount": {
      "button": 33,
      "combobox": 3,
      "form": 1,
      "formViewer": 2,
      "gallery": 5,
      "galleryTemplate": 5,
      "groupContainer": 7,
      "icon": 6,
      "image": 4,
      "label": 71,
      "rectangle": 15,
      "screen": 7,
      "text": 4,
      "typedDataCard": 19
    },
    "DeserializationLoadTime": 2.304925
  },
  "WasLocalDatabaseReferencesEmpty": false
}